pyfont/__init__.py
pyfont/api.py
pyfont/draw_by_html.py
pyfont/font.py
pyfont/html_to_image.py
pyfont-0.0.3.20041618.dist-info/LICENSE
pyfont-0.0.3.20041618.dist-info/METADATA
pyfont-0.0.3.20041618.dist-info/WHEEL
pyfont-0.0.3.20041618.dist-info/top_level.txt
pyfont-0.0.3.20041618.dist-info/RECORD
