Metadata-Version: 2.1
Name: pyfont
Version: 0.0.3.20041618
Summary: 生成文字图片
Home-page: https://github.com/BingerYang/pyfont
Author: binger
Author-email: <xuehen_521@126.com>
Maintainer: binger
Maintainer-email: <xuehen_521@126.com>
License: MITT
Platform: all
Requires-Python: >=3.4
